apollo_config_sdk/__init__.py
apollo_config_sdk/appdirs.py
apollo_config_sdk/client.py
apollo_config_sdk/filecache.py
apollo_config_sdk/main.py
apollo_config_sdk/readwritelock.py
apollo_config_sdk-0.1.3.dist-info/WHEEL
apollo_config_sdk-0.1.3.dist-info/METADATA
apollo_config_sdk-0.1.3.dist-info/RECORD
